{"lastUsed":1583390342274,"path":"E:\/FB3\/workspace\/myssi","projectCount":1,"recentFiles":[{"path":"\/myssiProject\/WebContent","parentWorkspace":"E:\/FB3\/workspace\/myssi","name":"dept.jsp","lastModified":1583389439052,"locationURI":"file:\/E:\/FB3\/workspace\/myssi\/myssiProject\/WebContent\/dept.jsp"},{"path":"\/myssiProject\/WebContent\/WEB-INF","parentWorkspace":"E:\/FB3\/workspace\/myssi","name":"applicationContext-ibatis.xml","lastModified":1583302147591,"locationURI":"file:\/E:\/FB3\/workspace\/myssi\/myssiProject\/WebContent\/WEB-INF\/applicationContext-ibatis.xml"},{"path":"\/myssiProject\/src","parentWorkspace":"E:\/FB3\/workspace\/myssi","name":"ApplicationResources.properties","lastModified":1583390342274,"locationURI":"file:\/E:\/FB3\/workspace\/myssi\/myssiProject\/src\/ApplicationResources.properties"},{"path":"\/myssiProject\/src\/myssiProject\/com\/hao\/detp\/action","parentWorkspace":"E:\/FB3\/workspace\/myssi","name":"DeptAction.java","lastModified":1583389842323,"locationURI":"file:\/E:\/FB3\/workspace\/myssi\/myssiProject\/src\/myssiProject\/com\/hao\/detp\/action\/DeptAction.java"},{"path":"\/myssiProject\/src\/myssiProject\/com\/hao\/detp\/dao","parentWorkspace":"E:\/FB3\/workspace\/myssi","name":"DeptDao.java","lastModified":1583303920655,"locationURI":"file:\/E:\/FB3\/workspace\/myssi\/myssiProject\/src\/myssiProject\/com\/hao\/detp\/dao\/DeptDao.java"},{"path":"\/myssiProject\/WebContent","parentWorkspace":"E:\/FB3\/workspace\/myssi","name":"dept2.jsp","lastModified":1583389813022,"locationURI":"file:\/E:\/FB3\/workspace\/myssi\/myssiProject\/WebContent\/dept2.jsp"},{"path":"\/myssiProject\/src\/myssiProject\/com\/hao\/detp\/service","parentWorkspace":"E:\/FB3\/workspace\/myssi","name":"DeptManager.java","lastModified":1583304256201,"locationURI":"file:\/E:\/FB3\/workspace\/myssi\/myssiProject\/src\/myssiProject\/com\/hao\/detp\/service\/DeptManager.java"},{"path":"\/myssiProject\/src\/myssiProject\/com\/hao\/detp\/dao\/ibatis","parentWorkspace":"E:\/FB3\/workspace\/myssi","name":"detp-sql.xml","lastModified":1583316637256,"locationURI":"file:\/E:\/FB3\/workspace\/myssi\/myssiProject\/src\/myssiProject\/com\/hao\/detp\/dao\/ibatis\/detp-sql.xml"},{"path":"\/myssiProject\/src\/myssiProject\/com\/hao\/detp\/vo","parentWorkspace":"E:\/FB3\/workspace\/myssi","name":"DeptInfo.java","lastModified":1583309612697,"locationURI":"file:\/E:\/FB3\/workspace\/myssi\/myssiProject\/src\/myssiProject\/com\/hao\/detp\/vo\/DeptInfo.java"},{"path":"\/myssiProject\/WebContent","parentWorkspace":"E:\/FB3\/workspace\/myssi","name":"showDeptInfo.jsp","lastModified":1583387482810,"locationURI":"file:\/E:\/FB3\/workspace\/myssi\/myssiProject\/WebContent\/showDeptInfo.jsp"},{"path":"\/myssiProject\/src\/myssiProject\/com\/hao\/detp\/service\/impl","parentWorkspace":"E:\/FB3\/workspace\/myssi","name":"DeptManagerImpl.java","lastModified":1583307784611,"locationURI":"file:\/E:\/FB3\/workspace\/myssi\/myssiProject\/src\/myssiProject\/com\/hao\/detp\/service\/impl\/DeptManagerImpl.java"},{"path":"\/myssiProject\/WebContent","parentWorkspace":"E:\/FB3\/workspace\/myssi","name":"success.jsp","lastModified":1583377101706,"locationURI":"file:\/E:\/FB3\/workspace\/myssi\/myssiProject\/WebContent\/success.jsp"},{"path":"\/myssiProject\/WebContent","parentWorkspace":"E:\/FB3\/workspace\/myssi","name":"error.jsp","lastModified":1583377090745,"locationURI":"file:\/E:\/FB3\/workspace\/myssi\/myssiProject\/WebContent\/error.jsp"},{"path":"\/myssiProject\/WebContent\/WEB-INF","parentWorkspace":"E:\/FB3\/workspace\/myssi","name":"struts-config.xml","lastModified":1583326901032,"locationURI":"file:\/E:\/FB3\/workspace\/myssi\/myssiProject\/WebContent\/WEB-INF\/struts-config.xml"},{"path":"\/myssiProject\/src\/myssiProject\/com\/hao\/detp\/actionForm","parentWorkspace":"E:\/FB3\/workspace\/myssi","name":"DeptActionForm.java","lastModified":1583291553996,"locationURI":"file:\/E:\/FB3\/workspace\/myssi\/myssiProject\/src\/myssiProject\/com\/hao\/detp\/actionForm\/DeptActionForm.java"},{"path":"\/myssiProject\/src\/myssiProject\/com\/hao\/detp\/dao\/ibatis","parentWorkspace":"E:\/FB3\/workspace\/myssi","name":"DeptDaoImpl.java","lastModified":1583303990083,"locationURI":"file:\/E:\/FB3\/workspace\/myssi\/myssiProject\/src\/myssiProject\/com\/hao\/detp\/dao\/ibatis\/DeptDaoImpl.java"},{"path":"\/myssiProject\/src\/myssiProject\/com\/hao\/detp\/action","parentWorkspace":"E:\/FB3\/workspace\/myssi","name":"BaseDispatchAction.java","lastModified":1583307515171,"locationURI":"file:\/E:\/FB3\/workspace\/myssi\/myssiProject\/src\/myssiProject\/com\/hao\/detp\/action\/BaseDispatchAction.java"},{"path":"\/myssiProject\/src\/myssiProject\/com\/hao\/detp\/dao\/ibatis","parentWorkspace":"E:\/FB3\/workspace\/myssi","name":"sql-map-config.xml","lastModified":1583291328130,"locationURI":"file:\/E:\/FB3\/workspace\/myssi\/myssiProject\/src\/myssiProject\/com\/hao\/detp\/dao\/ibatis\/sql-map-config.xml"},{"path":"\/myssiProject\/WebContent\/WEB-INF","parentWorkspace":"E:\/FB3\/workspace\/myssi","name":"applicationContext.xml","lastModified":1583290821622,"locationURI":"file:\/E:\/FB3\/workspace\/myssi\/myssiProject\/WebContent\/WEB-INF\/applicationContext.xml"},{"path":"\/myssiProject\/WebContent\/WEB-INF","parentWorkspace":"E:\/FB3\/workspace\/myssi","name":"web.xml","lastModified":1583293781780,"locationURI":"file:\/E:\/FB3\/workspace\/myssi\/myssiProject\/WebContent\/WEB-INF\/web.xml"}]}